streamlit_social_share/__init__.py
streamlit_social_share/frontend/index.html
streamlit_social_share/frontend/main.js
streamlit_social_share/frontend/streamlit-component-lib.js
streamlit_social_share/frontend/style.css
streamlit_social_share-0.1.0.dist-info/licenses/LICENSE
streamlit_social_share-0.1.0.dist-info/METADATA
streamlit_social_share-0.1.0.dist-info/WHEEL
streamlit_social_share-0.1.0.dist-info/top_level.txt
streamlit_social_share-0.1.0.dist-info/RECORD
