Metadata-Version: 2.4
Name: streamlit-social-share
Version: 0.1.0
Summary: Streamlit component that allows you to share your data via the native browser functionality
Author: julian
Author-email: bob@example.com
Requires-Python: >=3.7
License-File: LICENSE
Requires-Dist: streamlit>=1.2
Requires-Dist: jinja2
Dynamic: author
Dynamic: author-email
Dynamic: description
Dynamic: description-content-type
Dynamic: license-file
Dynamic: requires-dist
Dynamic: requires-python
Dynamic: summary
